vaultsphere/__init__.py
vaultsphere/cli.py
vaultsphere/core.py
vaultsphere/crypto.py
vaultsphere/index.py
vaultsphere/schema.py
vaultsphere/utils.py
vaultsphere-1.0.3.dist-info/licenses/LICENSE
vaultsphere-1.0.3.dist-info/METADATA
vaultsphere-1.0.3.dist-info/WHEEL
vaultsphere-1.0.3.dist-info/entry_points.txt
vaultsphere-1.0.3.dist-info/top_level.txt
vaultsphere-1.0.3.dist-info/RECORD
