Metadata-Version: 2.4
Name: vaultsphere
Version: 1.0.3
Summary: VaultSphere - A simple encrypted NoSQL-like database with base64 encoding.
Author: zzzNeet
License: MIT License
Requires-Python: >=3.7
License-File: LICENSE
Requires-Dist: cryptography>=41.0.0
Dynamic: license-file
Dynamic: requires-python
